<?xml version="1.0" encoding="utf-8" ?>
<c2eventsheet>
    <!--All the 'name' attributes are ignored by Construct 2 - they are there for readability only.-->
    <name>Loader</name>
    <events>
        <event-block sid="216783809975704">
            <conditions>
                <condition id="-8" name="Compare two values" sid="582603603931115" type="System">
                    <param id="0" name="First value">loadingprogress</param>
                    <param id="1" name="Comparison">4</param>
                    <param id="2" name="Second value">0.99</param>
                </condition>
            </conditions>
            <actions>
                <action id="-16" name="Wait" sid="403146728889880" type="System">
                    <param id="0" name="Seconds">1.0</param>
                </action>
                <action id="-2" name="Go to layout" sid="166325411624241" type="System">
                    <param id="0" name="Layout">Menu</param>
                </action>
            </actions>
        </event-block>
        <event-block sid="533797486683327">
            <conditions>
                <condition id="-1" name="Every tick" sid="362007881683863" type="System" />
            </conditions>
            <actions>
                <action id="-5" name="Set width" sid="233023848239800" type="loaderProgress">
                    <param id="0" name="Width">lerp(loaderProgress.Width, 250 * loadingprogress, 0.05)</param>
                </action>
                <action id="0" name="Set text" sid="375986304064520" type="textDebug">
                    <param id="0" name="Text">loadingprogress</param>
                </action>
            </actions>
        </event-block>
    </events>
</c2eventsheet>
