<?xml version="1.0" encoding="utf-8" ?>
<c2layout>
    <name>Game</name>
    <sid>464209801128605</sid>
    <event-sheet>Game</event-sheet>
    <size>
        <width>640</width>
        <height>960</height>
    </size>
    <margins>
        <horizontal>500</horizontal>
        <vertical>500</vertical>
    </margins>
    <unbounded-scrolling>0</unbounded-scrolling>
    <layers>
        <layer name="BG" sid="365177438595820">
            <initially-visible>1</initially-visible>
            <background-color>153,204,0</background-color>
            <transparent>0</transparent>
            <parallax>
                <x>1</x>
                <y>1</y>
            </parallax>
            <zoom-rate>1</zoom-rate>
            <opacity>1</opacity>
            <force-own-texture>0</force-own-texture>
            <global>0</global>
            <use-render-cells>0</use-render-cells>
            <blend-mode>0</blend-mode>
            <effect-fallback>0</effect-fallback>
            <instances>
                <instance type="TiledBackground" uid="19">
                    <properties>
                        <initial-visibility>Visible</initial-visibility>
                        <hotspot>Top-left</hotspot>
                    </properties>
                    <instance-variables>
                        <disroy>0</disroy>
                    </instance-variables>
                    <behavior-instances>
                        <behavior-instance type="Fade">
                            <properties>
                                <active-at-start>No</active-at-start>
                                <fade-in-time>1</fade-in-time>
                                <wait-time>0</wait-time>
                                <fade-out-time>0</fade-out-time>
                                <destroy>After fade out</destroy>
                            </properties>
                        </behavior-instance>
                        <behavior-instance type="Fade2">
                            <properties>
                                <active-at-start>No</active-at-start>
                                <fade-in-time>0</fade-in-time>
                                <wait-time>0</wait-time>
                                <fade-out-time>1</fade-out-time>
                                <destroy>After fade out</destroy>
                            </properties>
                        </behavior-instance>
                    </behavior-instances>
                    <blend-mode>0</blend-mode>
                    <effect-fallback>0</effect-fallback>
                    <world>
                        <x>0</x>
                        <y>0</y>
                        <z>0</z>
                        <width>640</width>
                        <height>960</height>
                        <depth>0</depth>
                        <hotspotX>0</hotspotX>
                        <hotspotY>0</hotspotY>
                        <angle>0</angle>
                        <opacity>1</opacity>
                    </world>
                </instance>
                <instance type="TiledBackground2" uid="39">
                    <properties>
                        <initial-visibility>Visible</initial-visibility>
                        <hotspot>Top-left</hotspot>
                    </properties>
                    <instance-variables>
                        <disroy>0</disroy>
                    </instance-variables>
                    <behavior-instances>
                        <behavior-instance type="Fade">
                            <properties>
                                <active-at-start>No</active-at-start>
                                <fade-in-time>1</fade-in-time>
                                <wait-time>0</wait-time>
                                <fade-out-time>0</fade-out-time>
                                <destroy>After fade out</destroy>
                            </properties>
                        </behavior-instance>
                        <behavior-instance type="Fade2">
                            <properties>
                                <active-at-start>No</active-at-start>
                                <fade-in-time>0</fade-in-time>
                                <wait-time>0</wait-time>
                                <fade-out-time>1</fade-out-time>
                                <destroy>After fade out</destroy>
                            </properties>
                        </behavior-instance>
                    </behavior-instances>
                    <blend-mode>0</blend-mode>
                    <effect-fallback>0</effect-fallback>
                    <world>
                        <x>28</x>
                        <y>18</y>
                        <z>0</z>
                        <width>591</width>
                        <height>921</height>
                        <depth>0</depth>
                        <hotspotX>0</hotspotX>
                        <hotspotY>0</hotspotY>
                        <angle>0</angle>
                        <opacity>1</opacity>
                    </world>
                </instance>
                <instance type="TiledBackground3" uid="41">
                    <properties>
                        <initial-visibility>Visible</initial-visibility>
                        <hotspot>Top-left</hotspot>
                    </properties>
                    <instance-variables>
                        <disroy>0</disroy>
                    </instance-variables>
                    <behavior-instances>
                        <behavior-instance type="Fade">
                            <properties>
                                <active-at-start>No</active-at-start>
                                <fade-in-time>1</fade-in-time>
                                <wait-time>0</wait-time>
                                <fade-out-time>0</fade-out-time>
                                <destroy>After fade out</destroy>
                            </properties>
                        </behavior-instance>
                        <behavior-instance type="Fade2">
                            <properties>
                                <active-at-start>No</active-at-start>
                                <fade-in-time>0</fade-in-time>
                                <wait-time>0</wait-time>
                                <fade-out-time>1</fade-out-time>
                                <destroy>After fade out</destroy>
                            </properties>
                        </behavior-instance>
                    </behavior-instances>
                    <blend-mode>0</blend-mode>
                    <effect-fallback>0</effect-fallback>
                    <world>
                        <x>57</x>
                        <y>43</y>
                        <z>0</z>
                        <width>532</width>
                        <height>867</height>
                        <depth>0</depth>
                        <hotspotX>0</hotspotX>
                        <hotspotY>0</hotspotY>
                        <angle>0</angle>
                        <opacity>1</opacity>
                    </world>
                </instance>
                <instance type="TiledBackground4" uid="42">
                    <properties>
                        <initial-visibility>Visible</initial-visibility>
                        <hotspot>Top-left</hotspot>
                    </properties>
                    <instance-variables>
                        <disroy>0</disroy>
                    </instance-variables>
                    <behavior-instances>
                        <behavior-instance type="Fade">
                            <properties>
                                <active-at-start>No</active-at-start>
                                <fade-in-time>1</fade-in-time>
                                <wait-time>0</wait-time>
                                <fade-out-time>0</fade-out-time>
                                <destroy>After fade out</destroy>
                            </properties>
                        </behavior-instance>
                        <behavior-instance type="Fade2">
                            <properties>
                                <active-at-start>No</active-at-start>
                                <fade-in-time>0</fade-in-time>
                                <wait-time>0</wait-time>
                                <fade-out-time>1</fade-out-time>
                                <destroy>After fade out</destroy>
                            </properties>
                        </behavior-instance>
                    </behavior-instances>
                    <blend-mode>0</blend-mode>
                    <effect-fallback>0</effect-fallback>
                    <world>
                        <x>83</x>
                        <y>76</y>
                        <z>0</z>
                        <width>473</width>
                        <height>804</height>
                        <depth>0</depth>
                        <hotspotX>0</hotspotX>
                        <hotspotY>0</hotspotY>
                        <angle>0</angle>
                        <opacity>1</opacity>
                    </world>
                </instance>
                <instance type="TiledBackground5" uid="43">
                    <properties>
                        <initial-visibility>Visible</initial-visibility>
                        <hotspot>Top-left</hotspot>
                    </properties>
                    <instance-variables>
                        <disroy>0</disroy>
                    </instance-variables>
                    <behavior-instances>
                        <behavior-instance type="Fade">
                            <properties>
                                <active-at-start>No</active-at-start>
                                <fade-in-time>1</fade-in-time>
                                <wait-time>0</wait-time>
                                <fade-out-time>0</fade-out-time>
                                <destroy>After fade out</destroy>
                            </properties>
                        </behavior-instance>
                        <behavior-instance type="Fade2">
                            <properties>
                                <active-at-start>No</active-at-start>
                                <fade-in-time>0</fade-in-time>
                                <wait-time>0</wait-time>
                                <fade-out-time>1</fade-out-time>
                                <destroy>After fade out</destroy>
                            </properties>
                        </behavior-instance>
                    </behavior-instances>
                    <blend-mode>0</blend-mode>
                    <effect-fallback>0</effect-fallback>
                    <world>
                        <x>92</x>
                        <y>98</y>
                        <z>0</z>
                        <width>435</width>
                        <height>747</height>
                        <depth>0</depth>
                        <hotspotX>0</hotspotX>
                        <hotspotY>0</hotspotY>
                        <angle>0</angle>
                        <opacity>1</opacity>
                    </world>
                </instance>
            </instances>
            <effects />
        </layer>
        <layer name="MG" sid="548107871418780">
            <initially-visible>1</initially-visible>
            <background-color>255,255,255</background-color>
            <transparent>1</transparent>
            <parallax>
                <x>1</x>
                <y>1</y>
            </parallax>
            <zoom-rate>1</zoom-rate>
            <opacity>1</opacity>
            <force-own-texture>0</force-own-texture>
            <global>0</global>
            <use-render-cells>0</use-render-cells>
            <blend-mode>0</blend-mode>
            <effect-fallback>0</effect-fallback>
            <instances>
                <instance type="BambooMG" uid="23">
                    <properties>
                        <initial-visibility>Visible</initial-visibility>
                        <initial-animation>Default</initial-animation>
                        <initial-frame>0</initial-frame>
                        <collisions>Enabled</collisions>
                    </properties>
                    <blend-mode>0</blend-mode>
                    <effect-fallback>0</effect-fallback>
                    <world>
                        <x>138</x>
                        <y>865</y>
                        <z>0</z>
                        <width>184</width>
                        <height>391</height>
                        <depth>0</depth>
                        <hotspotX>0.5</hotspotX>
                        <hotspotY>0.49360615</hotspotY>
                        <angle>0</angle>
                        <opacity>1</opacity>
                    </world>
                </instance>
                <instance type="BambooMG" uid="47">
                    <properties>
                        <initial-visibility>Visible</initial-visibility>
                        <initial-animation>Default</initial-animation>
                        <initial-frame>0</initial-frame>
                        <collisions>Enabled</collisions>
                    </properties>
                    <blend-mode>0</blend-mode>
                    <effect-fallback>0</effect-fallback>
                    <world>
                        <x>138</x>
                        <y>556</y>
                        <z>0</z>
                        <width>184</width>
                        <height>391</height>
                        <depth>0</depth>
                        <hotspotX>0.5</hotspotX>
                        <hotspotY>0.49360615</hotspotY>
                        <angle>0</angle>
                        <opacity>1</opacity>
                    </world>
                </instance>
                <instance type="BambooMG" uid="48">
                    <properties>
                        <initial-visibility>Visible</initial-visibility>
                        <initial-animation>Default</initial-animation>
                        <initial-frame>0</initial-frame>
                        <collisions>Enabled</collisions>
                    </properties>
                    <blend-mode>0</blend-mode>
                    <effect-fallback>0</effect-fallback>
                    <world>
                        <x>138</x>
                        <y>247</y>
                        <z>0</z>
                        <width>184</width>
                        <height>391</height>
                        <depth>0</depth>
                        <hotspotX>0.5</hotspotX>
                        <hotspotY>0.49360615</hotspotY>
                        <angle>0</angle>
                        <opacity>1</opacity>
                    </world>
                </instance>
                <instance type="BambooMG" uid="49">
                    <properties>
                        <initial-visibility>Visible</initial-visibility>
                        <initial-animation>Default</initial-animation>
                        <initial-frame>0</initial-frame>
                        <collisions>Enabled</collisions>
                    </properties>
                    <blend-mode>0</blend-mode>
                    <effect-fallback>0</effect-fallback>
                    <world>
                        <x>138</x>
                        <y>-63</y>
                        <z>0</z>
                        <width>184</width>
                        <height>391</height>
                        <depth>0</depth>
                        <hotspotX>0.5</hotspotX>
                        <hotspotY>0.49360615</hotspotY>
                        <angle>0</angle>
                        <opacity>1</opacity>
                    </world>
                </instance>
                <instance type="BambooMG" uid="50">
                    <properties>
                        <initial-visibility>Visible</initial-visibility>
                        <initial-animation>Default</initial-animation>
                        <initial-frame>0</initial-frame>
                        <collisions>Enabled</collisions>
                    </properties>
                    <blend-mode>0</blend-mode>
                    <effect-fallback>0</effect-fallback>
                    <world>
                        <x>138</x>
                        <y>-373</y>
                        <z>0</z>
                        <width>184</width>
                        <height>391</height>
                        <depth>0</depth>
                        <hotspotX>0.5</hotspotX>
                        <hotspotY>0.49360615</hotspotY>
                        <angle>0</angle>
                        <opacity>1</opacity>
                    </world>
                </instance>
                <instance type="BambooMG" uid="51">
                    <properties>
                        <initial-visibility>Visible</initial-visibility>
                        <initial-animation>Default</initial-animation>
                        <initial-frame>0</initial-frame>
                        <collisions>Enabled</collisions>
                    </properties>
                    <blend-mode>0</blend-mode>
                    <effect-fallback>0</effect-fallback>
                    <world>
                        <x>494</x>
                        <y>865</y>
                        <z>0</z>
                        <width>184</width>
                        <height>391</height>
                        <depth>0</depth>
                        <hotspotX>0.5</hotspotX>
                        <hotspotY>0.49360615</hotspotY>
                        <angle>0</angle>
                        <opacity>1</opacity>
                    </world>
                </instance>
                <instance type="BambooMG" uid="52">
                    <properties>
                        <initial-visibility>Visible</initial-visibility>
                        <initial-animation>Default</initial-animation>
                        <initial-frame>0</initial-frame>
                        <collisions>Enabled</collisions>
                    </properties>
                    <blend-mode>0</blend-mode>
                    <effect-fallback>0</effect-fallback>
                    <world>
                        <x>494</x>
                        <y>556</y>
                        <z>0</z>
                        <width>184</width>
                        <height>391</height>
                        <depth>0</depth>
                        <hotspotX>0.5</hotspotX>
                        <hotspotY>0.49360615</hotspotY>
                        <angle>0</angle>
                        <opacity>1</opacity>
                    </world>
                </instance>
                <instance type="BambooMG" uid="53">
                    <properties>
                        <initial-visibility>Visible</initial-visibility>
                        <initial-animation>Default</initial-animation>
                        <initial-frame>0</initial-frame>
                        <collisions>Enabled</collisions>
                    </properties>
                    <blend-mode>0</blend-mode>
                    <effect-fallback>0</effect-fallback>
                    <world>
                        <x>494</x>
                        <y>247</y>
                        <z>0</z>
                        <width>184</width>
                        <height>391</height>
                        <depth>0</depth>
                        <hotspotX>0.5</hotspotX>
                        <hotspotY>0.49360615</hotspotY>
                        <angle>0</angle>
                        <opacity>1</opacity>
                    </world>
                </instance>
                <instance type="BambooMG" uid="54">
                    <properties>
                        <initial-visibility>Visible</initial-visibility>
                        <initial-animation>Default</initial-animation>
                        <initial-frame>0</initial-frame>
                        <collisions>Enabled</collisions>
                    </properties>
                    <blend-mode>0</blend-mode>
                    <effect-fallback>0</effect-fallback>
                    <world>
                        <x>494</x>
                        <y>-63</y>
                        <z>0</z>
                        <width>184</width>
                        <height>391</height>
                        <depth>0</depth>
                        <hotspotX>0.5</hotspotX>
                        <hotspotY>0.49360615</hotspotY>
                        <angle>0</angle>
                        <opacity>1</opacity>
                    </world>
                </instance>
                <instance type="BambooMG" uid="55">
                    <properties>
                        <initial-visibility>Visible</initial-visibility>
                        <initial-animation>Default</initial-animation>
                        <initial-frame>0</initial-frame>
                        <collisions>Enabled</collisions>
                    </properties>
                    <blend-mode>0</blend-mode>
                    <effect-fallback>0</effect-fallback>
                    <world>
                        <x>494</x>
                        <y>-373</y>
                        <z>0</z>
                        <width>184</width>
                        <height>391</height>
                        <depth>0</depth>
                        <hotspotX>0.5</hotspotX>
                        <hotspotY>0.49360615</hotspotY>
                        <angle>0</angle>
                        <opacity>1</opacity>
                    </world>
                </instance>
                <instance type="BambooMG" uid="56">
                    <properties>
                        <initial-visibility>Visible</initial-visibility>
                        <initial-animation>Default</initial-animation>
                        <initial-frame>0</initial-frame>
                        <collisions>Enabled</collisions>
                    </properties>
                    <blend-mode>0</blend-mode>
                    <effect-fallback>0</effect-fallback>
                    <world>
                        <x>615</x>
                        <y>865</y>
                        <z>0</z>
                        <width>184</width>
                        <height>391</height>
                        <depth>0</depth>
                        <hotspotX>0.5</hotspotX>
                        <hotspotY>0.49360615</hotspotY>
                        <angle>0</angle>
                        <opacity>1</opacity>
                    </world>
                </instance>
                <instance type="BambooMG" uid="57">
                    <properties>
                        <initial-visibility>Visible</initial-visibility>
                        <initial-animation>Default</initial-animation>
                        <initial-frame>0</initial-frame>
                        <collisions>Enabled</collisions>
                    </properties>
                    <blend-mode>0</blend-mode>
                    <effect-fallback>0</effect-fallback>
                    <world>
                        <x>615</x>
                        <y>556</y>
                        <z>0</z>
                        <width>184</width>
                        <height>391</height>
                        <depth>0</depth>
                        <hotspotX>0.5</hotspotX>
                        <hotspotY>0.49360615</hotspotY>
                        <angle>0</angle>
                        <opacity>1</opacity>
                    </world>
                </instance>
                <instance type="BambooMG" uid="58">
                    <properties>
                        <initial-visibility>Visible</initial-visibility>
                        <initial-animation>Default</initial-animation>
                        <initial-frame>0</initial-frame>
                        <collisions>Enabled</collisions>
                    </properties>
                    <blend-mode>0</blend-mode>
                    <effect-fallback>0</effect-fallback>
                    <world>
                        <x>615</x>
                        <y>247</y>
                        <z>0</z>
                        <width>184</width>
                        <height>391</height>
                        <depth>0</depth>
                        <hotspotX>0.5</hotspotX>
                        <hotspotY>0.49360615</hotspotY>
                        <angle>0</angle>
                        <opacity>1</opacity>
                    </world>
                </instance>
                <instance type="BambooMG" uid="59">
                    <properties>
                        <initial-visibility>Visible</initial-visibility>
                        <initial-animation>Default</initial-animation>
                        <initial-frame>0</initial-frame>
                        <collisions>Enabled</collisions>
                    </properties>
                    <blend-mode>0</blend-mode>
                    <effect-fallback>0</effect-fallback>
                    <world>
                        <x>615</x>
                        <y>-63</y>
                        <z>0</z>
                        <width>184</width>
                        <height>391</height>
                        <depth>0</depth>
                        <hotspotX>0.5</hotspotX>
                        <hotspotY>0.49360615</hotspotY>
                        <angle>0</angle>
                        <opacity>1</opacity>
                    </world>
                </instance>
                <instance type="BambooMG" uid="60">
                    <properties>
                        <initial-visibility>Visible</initial-visibility>
                        <initial-animation>Default</initial-animation>
                        <initial-frame>0</initial-frame>
                        <collisions>Enabled</collisions>
                    </properties>
                    <blend-mode>0</blend-mode>
                    <effect-fallback>0</effect-fallback>
                    <world>
                        <x>615</x>
                        <y>-373</y>
                        <z>0</z>
                        <width>184</width>
                        <height>391</height>
                        <depth>0</depth>
                        <hotspotX>0.5</hotspotX>
                        <hotspotY>0.49360615</hotspotY>
                        <angle>0</angle>
                        <opacity>1</opacity>
                    </world>
                </instance>
                <instance type="BambooMG" uid="61">
                    <properties>
                        <initial-visibility>Visible</initial-visibility>
                        <initial-animation>Default</initial-animation>
                        <initial-frame>0</initial-frame>
                        <collisions>Enabled</collisions>
                    </properties>
                    <blend-mode>0</blend-mode>
                    <effect-fallback>0</effect-fallback>
                    <world>
                        <x>16</x>
                        <y>865</y>
                        <z>0</z>
                        <width>184</width>
                        <height>391</height>
                        <depth>0</depth>
                        <hotspotX>0.5</hotspotX>
                        <hotspotY>0.49360615</hotspotY>
                        <angle>0</angle>
                        <opacity>1</opacity>
                    </world>
                </instance>
                <instance type="BambooMG" uid="62">
                    <properties>
                        <initial-visibility>Visible</initial-visibility>
                        <initial-animation>Default</initial-animation>
                        <initial-frame>0</initial-frame>
                        <collisions>Enabled</collisions>
                    </properties>
                    <blend-mode>0</blend-mode>
                    <effect-fallback>0</effect-fallback>
                    <world>
                        <x>16</x>
                        <y>556</y>
                        <z>0</z>
                        <width>184</width>
                        <height>391</height>
                        <depth>0</depth>
                        <hotspotX>0.5</hotspotX>
                        <hotspotY>0.49360615</hotspotY>
                        <angle>0</angle>
                        <opacity>1</opacity>
                    </world>
                </instance>
                <instance type="BambooMG" uid="63">
                    <properties>
                        <initial-visibility>Visible</initial-visibility>
                        <initial-animation>Default</initial-animation>
                        <initial-frame>0</initial-frame>
                        <collisions>Enabled</collisions>
                    </properties>
                    <blend-mode>0</blend-mode>
                    <effect-fallback>0</effect-fallback>
                    <world>
                        <x>16</x>
                        <y>247</y>
                        <z>0</z>
                        <width>184</width>
                        <height>391</height>
                        <depth>0</depth>
                        <hotspotX>0.5</hotspotX>
                        <hotspotY>0.49360615</hotspotY>
                        <angle>0</angle>
                        <opacity>1</opacity>
                    </world>
                </instance>
                <instance type="BambooMG" uid="64">
                    <properties>
                        <initial-visibility>Visible</initial-visibility>
                        <initial-animation>Default</initial-animation>
                        <initial-frame>0</initial-frame>
                        <collisions>Enabled</collisions>
                    </properties>
                    <blend-mode>0</blend-mode>
                    <effect-fallback>0</effect-fallback>
                    <world>
                        <x>16</x>
                        <y>-63</y>
                        <z>0</z>
                        <width>184</width>
                        <height>391</height>
                        <depth>0</depth>
                        <hotspotX>0.5</hotspotX>
                        <hotspotY>0.49360615</hotspotY>
                        <angle>0</angle>
                        <opacity>1</opacity>
                    </world>
                </instance>
                <instance type="BambooMG" uid="65">
                    <properties>
                        <initial-visibility>Visible</initial-visibility>
                        <initial-animation>Default</initial-animation>
                        <initial-frame>0</initial-frame>
                        <collisions>Enabled</collisions>
                    </properties>
                    <blend-mode>0</blend-mode>
                    <effect-fallback>0</effect-fallback>
                    <world>
                        <x>16</x>
                        <y>-373</y>
                        <z>0</z>
                        <width>184</width>
                        <height>391</height>
                        <depth>0</depth>
                        <hotspotX>0.5</hotspotX>
                        <hotspotY>0.49360615</hotspotY>
                        <angle>0</angle>
                        <opacity>1</opacity>
                    </world>
                </instance>
                <instance type="playerAbility" uid="86">
                    <properties>
                        <initial-visibility>Visible</initial-visibility>
                        <initial-animation>Default</initial-animation>
                        <initial-frame>0</initial-frame>
                        <collisions>Enabled</collisions>
                    </properties>
                    <behavior-instances>
                        <behavior-instance type="Fade">
                            <properties>
                                <active-at-start>No</active-at-start>
                                <fade-in-time>0</fade-in-time>
                                <wait-time>0</wait-time>
                                <fade-out-time>0.4</fade-out-time>
                                <destroy>After fade out</destroy>
                            </properties>
                        </behavior-instance>
                    </behavior-instances>
                    <blend-mode>0</blend-mode>
                    <effect-fallback>0</effect-fallback>
                    <world>
                        <x>986</x>
                        <y>-61</y>
                        <z>0</z>
                        <width>256</width>
                        <height>256</height>
                        <depth>0</depth>
                        <hotspotX>0.5</hotspotX>
                        <hotspotY>0.5</hotspotY>
                        <angle>0</angle>
                        <opacity>0.5</opacity>
                    </world>
                </instance>
            </instances>
            <effects />
        </layer>
        <layer name="FG" sid="190971560557065">
            <initially-visible>1</initially-visible>
            <background-color>255,255,255</background-color>
            <transparent>1</transparent>
            <parallax>
                <x>1</x>
                <y>1</y>
            </parallax>
            <zoom-rate>1</zoom-rate>
            <opacity>1</opacity>
            <force-own-texture>0</force-own-texture>
            <global>0</global>
            <use-render-cells>0</use-render-cells>
            <blend-mode>0</blend-mode>
            <effect-fallback>0</effect-fallback>
            <instances>
                <instance type="BambooL" uid="44">
                    <properties>
                        <initial-visibility>Visible</initial-visibility>
                        <initial-animation>Default</initial-animation>
                        <initial-frame>0</initial-frame>
                        <collisions>Enabled</collisions>
                    </properties>
                    <behavior-instances>
                        <behavior-instance type="Bullet">
                            <properties>
                                <speed>0</speed>
                                <acceleration>0</acceleration>
                                <gravity>50</gravity>
                                <bounce-off-solids>No</bounce-off-solids>
                                <set-angle>No</set-angle>
                                <initial-state>Disabled</initial-state>
                            </properties>
                        </behavior-instance>
                        <behavior-instance type="Fade">
                            <properties>
                                <active-at-start>No</active-at-start>
                                <fade-in-time>0</fade-in-time>
                                <wait-time>0</wait-time>
                                <fade-out-time>1</fade-out-time>
                                <destroy>After fade out</destroy>
                            </properties>
                        </behavior-instance>
                        <behavior-instance type="Flash" />
                    </behavior-instances>
                    <blend-mode>0</blend-mode>
                    <effect-fallback>0</effect-fallback>
                    <world>
                        <x>79.635505676</x>
                        <y>241</y>
                        <z>0</z>
                        <width>256</width>
                        <height>544</height>
                        <depth>0</depth>
                        <hotspotX>0.609375</hotspotX>
                        <hotspotY>0.5</hotspotY>
                        <angle>0</angle>
                        <opacity>1</opacity>
                    </world>
                </instance>
                <instance type="BambooM" uid="45">
                    <properties>
                        <initial-visibility>Visible</initial-visibility>
                        <initial-animation>Default</initial-animation>
                        <initial-frame>0</initial-frame>
                        <collisions>Enabled</collisions>
                    </properties>
                    <behavior-instances>
                        <behavior-instance type="Bullet">
                            <properties>
                                <speed>0</speed>
                                <acceleration>0</acceleration>
                                <gravity>50</gravity>
                                <bounce-off-solids>No</bounce-off-solids>
                                <set-angle>No</set-angle>
                                <initial-state>Disabled</initial-state>
                            </properties>
                        </behavior-instance>
                        <behavior-instance type="Fade">
                            <properties>
                                <active-at-start>No</active-at-start>
                                <fade-in-time>0</fade-in-time>
                                <wait-time>0</wait-time>
                                <fade-out-time>1</fade-out-time>
                                <destroy>After fade out</destroy>
                            </properties>
                        </behavior-instance>
                        <behavior-instance type="Flash" />
                    </behavior-instances>
                    <blend-mode>0</blend-mode>
                    <effect-fallback>0</effect-fallback>
                    <world>
                        <x>318.635498047</x>
                        <y>241.5</y>
                        <z>0</z>
                        <width>256</width>
                        <height>544</height>
                        <depth>0</depth>
                        <hotspotX>0.609375</hotspotX>
                        <hotspotY>0.5</hotspotY>
                        <angle>0</angle>
                        <opacity>1</opacity>
                    </world>
                </instance>
                <instance type="BambooR" uid="46">
                    <properties>
                        <initial-visibility>Visible</initial-visibility>
                        <initial-animation>Default</initial-animation>
                        <initial-frame>0</initial-frame>
                        <collisions>Enabled</collisions>
                    </properties>
                    <behavior-instances>
                        <behavior-instance type="Bullet">
                            <properties>
                                <speed>0</speed>
                                <acceleration>0</acceleration>
                                <gravity>50</gravity>
                                <bounce-off-solids>No</bounce-off-solids>
                                <set-angle>No</set-angle>
                                <initial-state>Disabled</initial-state>
                            </properties>
                        </behavior-instance>
                        <behavior-instance type="Fade">
                            <properties>
                                <active-at-start>No</active-at-start>
                                <fade-in-time>0</fade-in-time>
                                <wait-time>0</wait-time>
                                <fade-out-time>1</fade-out-time>
                                <destroy>After fade out</destroy>
                            </properties>
                        </behavior-instance>
                        <behavior-instance type="Flash" />
                    </behavior-instances>
                    <blend-mode>0</blend-mode>
                    <effect-fallback>0</effect-fallback>
                    <world>
                        <x>560.635498047</x>
                        <y>238.5</y>
                        <z>0</z>
                        <width>256</width>
                        <height>544</height>
                        <depth>0</depth>
                        <hotspotX>0.609375</hotspotX>
                        <hotspotY>0.5</hotspotY>
                        <angle>0</angle>
                        <opacity>1</opacity>
                    </world>
                </instance>
                <instance type="BambooL" uid="4">
                    <properties>
                        <initial-visibility>Visible</initial-visibility>
                        <initial-animation>Default</initial-animation>
                        <initial-frame>0</initial-frame>
                        <collisions>Enabled</collisions>
                    </properties>
                    <behavior-instances>
                        <behavior-instance type="Bullet">
                            <properties>
                                <speed>0</speed>
                                <acceleration>0</acceleration>
                                <gravity>50</gravity>
                                <bounce-off-solids>No</bounce-off-solids>
                                <set-angle>No</set-angle>
                                <initial-state>Disabled</initial-state>
                            </properties>
                        </behavior-instance>
                        <behavior-instance type="Fade">
                            <properties>
                                <active-at-start>No</active-at-start>
                                <fade-in-time>0</fade-in-time>
                                <wait-time>0</wait-time>
                                <fade-out-time>1</fade-out-time>
                                <destroy>After fade out</destroy>
                            </properties>
                        </behavior-instance>
                        <behavior-instance type="Flash" />
                    </behavior-instances>
                    <blend-mode>0</blend-mode>
                    <effect-fallback>0</effect-fallback>
                    <world>
                        <x>79.364501953</x>
                        <y>-278</y>
                        <z>0</z>
                        <width>256</width>
                        <height>544</height>
                        <depth>0</depth>
                        <hotspotX>0.609375</hotspotX>
                        <hotspotY>0.5</hotspotY>
                        <angle>0</angle>
                        <opacity>1</opacity>
                    </world>
                </instance>
                <instance type="BambooM" uid="5">
                    <properties>
                        <initial-visibility>Visible</initial-visibility>
                        <initial-animation>Default</initial-animation>
                        <initial-frame>0</initial-frame>
                        <collisions>Enabled</collisions>
                    </properties>
                    <behavior-instances>
                        <behavior-instance type="Bullet">
                            <properties>
                                <speed>0</speed>
                                <acceleration>0</acceleration>
                                <gravity>50</gravity>
                                <bounce-off-solids>No</bounce-off-solids>
                                <set-angle>No</set-angle>
                                <initial-state>Disabled</initial-state>
                            </properties>
                        </behavior-instance>
                        <behavior-instance type="Fade">
                            <properties>
                                <active-at-start>No</active-at-start>
                                <fade-in-time>0</fade-in-time>
                                <wait-time>0</wait-time>
                                <fade-out-time>1</fade-out-time>
                                <destroy>After fade out</destroy>
                            </properties>
                        </behavior-instance>
                        <behavior-instance type="Flash" />
                    </behavior-instances>
                    <blend-mode>0</blend-mode>
                    <effect-fallback>0</effect-fallback>
                    <world>
                        <x>318.364501953</x>
                        <y>-277</y>
                        <z>0</z>
                        <width>256</width>
                        <height>544</height>
                        <depth>0</depth>
                        <hotspotX>0.609375</hotspotX>
                        <hotspotY>0.5</hotspotY>
                        <angle>0</angle>
                        <opacity>1</opacity>
                    </world>
                </instance>
                <instance type="BambooR" uid="6">
                    <properties>
                        <initial-visibility>Visible</initial-visibility>
                        <initial-animation>Default</initial-animation>
                        <initial-frame>0</initial-frame>
                        <collisions>Enabled</collisions>
                    </properties>
                    <behavior-instances>
                        <behavior-instance type="Bullet">
                            <properties>
                                <speed>0</speed>
                                <acceleration>0</acceleration>
                                <gravity>50</gravity>
                                <bounce-off-solids>No</bounce-off-solids>
                                <set-angle>No</set-angle>
                                <initial-state>Disabled</initial-state>
                            </properties>
                        </behavior-instance>
                        <behavior-instance type="Fade">
                            <properties>
                                <active-at-start>No</active-at-start>
                                <fade-in-time>0</fade-in-time>
                                <wait-time>0</wait-time>
                                <fade-out-time>1</fade-out-time>
                                <destroy>After fade out</destroy>
                            </properties>
                        </behavior-instance>
                        <behavior-instance type="Flash" />
                    </behavior-instances>
                    <blend-mode>0</blend-mode>
                    <effect-fallback>0</effect-fallback>
                    <world>
                        <x>560.364501953</x>
                        <y>-280</y>
                        <z>0</z>
                        <width>256</width>
                        <height>544</height>
                        <depth>0</depth>
                        <hotspotX>0.609375</hotspotX>
                        <hotspotY>0.5</hotspotY>
                        <angle>0</angle>
                        <opacity>1</opacity>
                    </world>
                </instance>
                <instance type="BambooL" uid="15">
                    <properties>
                        <initial-visibility>Visible</initial-visibility>
                        <initial-animation>Default</initial-animation>
                        <initial-frame>0</initial-frame>
                        <collisions>Enabled</collisions>
                    </properties>
                    <behavior-instances>
                        <behavior-instance type="Bullet">
                            <properties>
                                <speed>0</speed>
                                <acceleration>0</acceleration>
                                <gravity>50</gravity>
                                <bounce-off-solids>No</bounce-off-solids>
                                <set-angle>No</set-angle>
                                <initial-state>Disabled</initial-state>
                            </properties>
                        </behavior-instance>
                        <behavior-instance type="Fade">
                            <properties>
                                <active-at-start>No</active-at-start>
                                <fade-in-time>0</fade-in-time>
                                <wait-time>0</wait-time>
                                <fade-out-time>1</fade-out-time>
                                <destroy>After fade out</destroy>
                            </properties>
                        </behavior-instance>
                        <behavior-instance type="Flash" />
                    </behavior-instances>
                    <blend-mode>0</blend-mode>
                    <effect-fallback>0</effect-fallback>
                    <world>
                        <x>79.364501953</x>
                        <y>764</y>
                        <z>0</z>
                        <width>256</width>
                        <height>544</height>
                        <depth>0</depth>
                        <hotspotX>0.609375</hotspotX>
                        <hotspotY>0.5</hotspotY>
                        <angle>0</angle>
                        <opacity>1</opacity>
                    </world>
                </instance>
                <instance type="BambooM" uid="21">
                    <properties>
                        <initial-visibility>Visible</initial-visibility>
                        <initial-animation>Default</initial-animation>
                        <initial-frame>0</initial-frame>
                        <collisions>Enabled</collisions>
                    </properties>
                    <behavior-instances>
                        <behavior-instance type="Bullet">
                            <properties>
                                <speed>0</speed>
                                <acceleration>0</acceleration>
                                <gravity>50</gravity>
                                <bounce-off-solids>No</bounce-off-solids>
                                <set-angle>No</set-angle>
                                <initial-state>Disabled</initial-state>
                            </properties>
                        </behavior-instance>
                        <behavior-instance type="Fade">
                            <properties>
                                <active-at-start>No</active-at-start>
                                <fade-in-time>0</fade-in-time>
                                <wait-time>0</wait-time>
                                <fade-out-time>1</fade-out-time>
                                <destroy>After fade out</destroy>
                            </properties>
                        </behavior-instance>
                        <behavior-instance type="Flash" />
                    </behavior-instances>
                    <blend-mode>0</blend-mode>
                    <effect-fallback>0</effect-fallback>
                    <world>
                        <x>318.364501953</x>
                        <y>764</y>
                        <z>0</z>
                        <width>256</width>
                        <height>544</height>
                        <depth>0</depth>
                        <hotspotX>0.609375</hotspotX>
                        <hotspotY>0.5</hotspotY>
                        <angle>0</angle>
                        <opacity>1</opacity>
                    </world>
                </instance>
                <instance type="BambooR" uid="22">
                    <properties>
                        <initial-visibility>Visible</initial-visibility>
                        <initial-animation>Default</initial-animation>
                        <initial-frame>0</initial-frame>
                        <collisions>Enabled</collisions>
                    </properties>
                    <behavior-instances>
                        <behavior-instance type="Bullet">
                            <properties>
                                <speed>0</speed>
                                <acceleration>0</acceleration>
                                <gravity>50</gravity>
                                <bounce-off-solids>No</bounce-off-solids>
                                <set-angle>No</set-angle>
                                <initial-state>Disabled</initial-state>
                            </properties>
                        </behavior-instance>
                        <behavior-instance type="Fade">
                            <properties>
                                <active-at-start>No</active-at-start>
                                <fade-in-time>0</fade-in-time>
                                <wait-time>0</wait-time>
                                <fade-out-time>1</fade-out-time>
                                <destroy>After fade out</destroy>
                            </properties>
                        </behavior-instance>
                        <behavior-instance type="Flash" />
                    </behavior-instances>
                    <blend-mode>0</blend-mode>
                    <effect-fallback>0</effect-fallback>
                    <world>
                        <x>560.364501953</x>
                        <y>761</y>
                        <z>0</z>
                        <width>256</width>
                        <height>544</height>
                        <depth>0</depth>
                        <hotspotX>0.609375</hotspotX>
                        <hotspotY>0.5</hotspotY>
                        <angle>0</angle>
                        <opacity>1</opacity>
                    </world>
                </instance>
            </instances>
            <effects />
        </layer>
        <layer name="game" sid="194207420014123">
            <initially-visible>1</initially-visible>
            <background-color>255,255,255</background-color>
            <transparent>1</transparent>
            <parallax>
                <x>1</x>
                <y>1</y>
            </parallax>
            <zoom-rate>1</zoom-rate>
            <opacity>1</opacity>
            <force-own-texture>0</force-own-texture>
            <global>0</global>
            <use-render-cells>0</use-render-cells>
            <blend-mode>0</blend-mode>
            <effect-fallback>0</effect-fallback>
            <instances>
                <instance type="destroyer" uid="1">
                    <properties>
                        <initial-visibility>Visible</initial-visibility>
                        <initial-animation>Default</initial-animation>
                        <initial-frame>0</initial-frame>
                        <collisions>Enabled</collisions>
                    </properties>
                    <blend-mode>0</blend-mode>
                    <effect-fallback>0</effect-fallback>
                    <world>
                        <x>320</x>
                        <y>1049</y>
                        <z>0</z>
                        <width>812</width>
                        <height>44</height>
                        <depth>0</depth>
                        <hotspotX>0.5</hotspotX>
                        <hotspotY>-2.230769157</hotspotY>
                        <angle>0</angle>
                        <opacity>1</opacity>
                    </world>
                </instance>
                <instance type="Coconut" uid="3">
                    <properties>
                        <initial-visibility>Visible</initial-visibility>
                        <initial-animation>Default</initial-animation>
                        <initial-frame>0</initial-frame>
                        <collisions>Enabled</collisions>
                    </properties>
                    <behavior-instances>
                        <behavior-instance type="Bullet">
                            <properties>
                                <speed>0</speed>
                                <acceleration>0</acceleration>
                                <gravity>50</gravity>
                                <bounce-off-solids>No</bounce-off-solids>
                                <set-angle>No</set-angle>
                                <initial-state>Enabled</initial-state>
                            </properties>
                        </behavior-instance>
                        <behavior-instance type="Rotate">
                            <properties>
                                <speed>180</speed>
                                <acceleration>0</acceleration>
                            </properties>
                        </behavior-instance>
                        <behavior-instance type="Platform">
                            <properties>
                                <max-speed>330</max-speed>
                                <acceleration>1500</acceleration>
                                <deceleration>1500</deceleration>
                                <jump-strength>650</jump-strength>
                                <gravity>1500</gravity>
                                <max-fall-speed>1000</max-fall-speed>
                                <double-jump>Disabled</double-jump>
                                <jump-sustain>0</jump-sustain>
                                <default-controls>No</default-controls>
                                <initial-state>Disabled</initial-state>
                            </properties>
                        </behavior-instance>
                    </behavior-instances>
                    <blend-mode>0</blend-mode>
                    <effect-fallback>0</effect-fallback>
                    <world>
                        <x>320</x>
                        <y>-62</y>
                        <z>0</z>
                        <width>124</width>
                        <height>117</height>
                        <depth>0</depth>
                        <hotspotX>0.5</hotspotX>
                        <hotspotY>0.504273534</hotspotY>
                        <angle>0</angle>
                        <opacity>1</opacity>
                    </world>
                </instance>
                <instance type="jumper" uid="2">
                    <properties>
                        <initial-visibility>Invisible</initial-visibility>
                        <initial-animation>Default</initial-animation>
                        <initial-frame>0</initial-frame>
                        <collisions>Enabled</collisions>
                    </properties>
                    <blend-mode>0</blend-mode>
                    <effect-fallback>0</effect-fallback>
                    <world>
                        <x>317</x>
                        <y>726</y>
                        <z>0</z>
                        <width>74</width>
                        <height>80</height>
                        <depth>0</depth>
                        <hotspotX>0.5</hotspotX>
                        <hotspotY>0.5</hotspotY>
                        <angle>0</angle>
                        <opacity>1</opacity>
                    </world>
                </instance>
                <instance type="Spawnerleft" uid="28">
                    <properties>
                        <initial-visibility>Invisible</initial-visibility>
                        <initial-animation>Default</initial-animation>
                        <initial-frame>0</initial-frame>
                        <collisions>Enabled</collisions>
                    </properties>
                    <behavior-instances>
                        <behavior-instance type="Timer" />
                    </behavior-instances>
                    <blend-mode>0</blend-mode>
                    <effect-fallback>0</effect-fallback>
                    <world>
                        <x>70</x>
                        <y>-275</y>
                        <z>0</z>
                        <width>57</width>
                        <height>50</height>
                        <depth>0</depth>
                        <hotspotX>0.5</hotspotX>
                        <hotspotY>0.5</hotspotY>
                        <angle>0</angle>
                        <opacity>1</opacity>
                    </world>
                </instance>
                <instance type="spawnerMid" uid="29">
                    <properties>
                        <initial-visibility>Invisible</initial-visibility>
                        <initial-animation>Default</initial-animation>
                        <initial-frame>0</initial-frame>
                        <collisions>Enabled</collisions>
                    </properties>
                    <behavior-instances>
                        <behavior-instance type="Timer" />
                    </behavior-instances>
                    <blend-mode>0</blend-mode>
                    <effect-fallback>0</effect-fallback>
                    <world>
                        <x>312</x>
                        <y>-360</y>
                        <z>0</z>
                        <width>58</width>
                        <height>58</height>
                        <depth>0</depth>
                        <hotspotX>0.5</hotspotX>
                        <hotspotY>0.5</hotspotY>
                        <angle>0</angle>
                        <opacity>1</opacity>
                    </world>
                </instance>
                <instance type="SpawnerRight" uid="30">
                    <properties>
                        <initial-visibility>Invisible</initial-visibility>
                        <initial-animation>Default</initial-animation>
                        <initial-frame>0</initial-frame>
                        <collisions>Enabled</collisions>
                    </properties>
                    <behavior-instances>
                        <behavior-instance type="Timer" />
                    </behavior-instances>
                    <blend-mode>0</blend-mode>
                    <effect-fallback>0</effect-fallback>
                    <world>
                        <x>552</x>
                        <y>-271</y>
                        <z>0</z>
                        <width>58</width>
                        <height>58</height>
                        <depth>0</depth>
                        <hotspotX>0.5</hotspotX>
                        <hotspotY>0.5</hotspotY>
                        <angle>0</angle>
                        <opacity>1</opacity>
                    </world>
                </instance>
                <instance type="Particles2" uid="31">
                    <properties>
                        <rate>250</rate>
                        <spray-cone>270</spray-cone>
                        <type>One-shot</type>
                        <initial-particle-properties></initial-particle-properties>
                        <speed>100</speed>
                        <size>20</size>
                        <opacity>100</opacity>
                        <grow-rate>0</grow-rate>
                        <x-randomiser>10</x-randomiser>
                        <y-randomiser>10</y-randomiser>
                        <speed-randomiser->100</speed-randomiser->
                        <size-randomiser>5</size-randomiser>
                        <grow-rate-randomiser>0</grow-rate-randomiser>
                        <particle-lifetime-properties></particle-lifetime-properties>
                        <acceleration>-150</acceleration>
                        <gravity>5</gravity>
                        <angle-randomiser>0</angle-randomiser>
                        <speed-randomiser>800</speed-randomiser>
                        <opacity-randomiser>0</opacity-randomiser>
                        <destroy-mode>Fade to invisible</destroy-mode>
                        <timeout>1</timeout>
                    </properties>
                    <blend-mode>0</blend-mode>
                    <effect-fallback>0</effect-fallback>
                    <world>
                        <x>1035</x>
                        <y>335</y>
                        <z>0</z>
                        <width>128</width>
                        <height>128</height>
                        <depth>0</depth>
                        <hotspotX>0</hotspotX>
                        <hotspotY>0.5</hotspotY>
                        <angle>0</angle>
                        <opacity>1</opacity>
                    </world>
                </instance>
                <instance type="rester2" uid="40">
                    <properties>
                        <initial-visibility>Visible</initial-visibility>
                        <initial-animation>Default</initial-animation>
                        <initial-frame>0</initial-frame>
                        <collisions>Enabled</collisions>
                    </properties>
                    <blend-mode>0</blend-mode>
                    <effect-fallback>0</effect-fallback>
                    <world>
                        <x>-550</x>
                        <y>-492</y>
                        <z>0</z>
                        <width>656</width>
                        <height>39</height>
                        <depth>0</depth>
                        <hotspotX>0.496031731</hotspotX>
                        <hotspotY>0.358974367</hotspotY>
                        <angle>0</angle>
                        <opacity>1</opacity>
                    </world>
                </instance>
                <instance type="player" uid="38">
                    <properties>
                        <initial-visibility>Visible</initial-visibility>
                        <initial-animation>Default</initial-animation>
                        <initial-frame>0</initial-frame>
                        <collisions>Enabled</collisions>
                    </properties>
                    <behavior-instances>
                        <behavior-instance type="Turret">
                            <properties>
                                <range>1000000</range>
                                <rate-of-fire>1</rate-of-fire>
                                <rotate>Yes</rotate>
                                <rotate-speed>180</rotate-speed>
                                <target-mode>First in range</target-mode>
                                <predictive-aim>No</predictive-aim>
                                <projectile-speed>500</projectile-speed>
                                <initial-state>Enabled</initial-state>
                                <use-collision-cells>Yes</use-collision-cells>
                            </properties>
                        </behavior-instance>
                    </behavior-instances>
                    <blend-mode>0</blend-mode>
                    <effect-fallback>0</effect-fallback>
                    <world>
                        <x>320</x>
                        <y>1365</y>
                        <z>0</z>
                        <width>100</width>
                        <height>100</height>
                        <depth>0</depth>
                        <hotspotX>0.5</hotspotX>
                        <hotspotY>0.5</hotspotY>
                        <angle>0</angle>
                        <opacity>1</opacity>
                    </world>
                </instance>
                <instance type="PlayerAnimations" uid="0">
                    <properties>
                        <initial-visibility>Visible</initial-visibility>
                        <initial-animation>Default</initial-animation>
                        <initial-frame>0</initial-frame>
                        <collisions>Enabled</collisions>
                    </properties>
                    <behavior-instances>
                        <behavior-instance type="Pin" />
                        <behavior-instance type="Platform">
                            <properties>
                                <max-speed>0</max-speed>
                                <acceleration>1500</acceleration>
                                <deceleration>1500</deceleration>
                                <jump-strength>650</jump-strength>
                                <gravity>1500</gravity>
                                <max-fall-speed>1000</max-fall-speed>
                                <double-jump>Disabled</double-jump>
                                <jump-sustain>0</jump-sustain>
                                <default-controls>No</default-controls>
                                <initial-state>Disabled</initial-state>
                            </properties>
                        </behavior-instance>
                        <behavior-instance type="Rotate">
                            <properties>
                                <speed>0</speed>
                                <acceleration>0</acceleration>
                            </properties>
                        </behavior-instance>
                    </behavior-instances>
                    <blend-mode>0</blend-mode>
                    <effect-fallback>0</effect-fallback>
                    <world>
                        <x>-174</x>
                        <y>836</y>
                        <z>0</z>
                        <width>105</width>
                        <height>306</height>
                        <depth>0</depth>
                        <hotspotX>0.504761934</hotspotX>
                        <hotspotY>0.5</hotspotY>
                        <angle>0</angle>
                        <opacity>1</opacity>
                    </world>
                </instance>
                <instance type="berryBig" uid="96">
                    <properties>
                        <initial-visibility>Visible</initial-visibility>
                        <initial-animation>Default</initial-animation>
                        <initial-frame>0</initial-frame>
                        <collisions>Enabled</collisions>
                    </properties>
                    <behavior-instances>
                        <behavior-instance type="Bullet">
                            <properties>
                                <speed>0</speed>
                                <acceleration>0</acceleration>
                                <gravity>150</gravity>
                                <bounce-off-solids>No</bounce-off-solids>
                                <set-angle>No</set-angle>
                                <initial-state>Enabled</initial-state>
                            </properties>
                        </behavior-instance>
                        <behavior-instance type="Rotate">
                            <properties>
                                <speed>180</speed>
                                <acceleration>0</acceleration>
                            </properties>
                        </behavior-instance>
                        <behavior-instance type="Platform">
                            <properties>
                                <max-speed>330</max-speed>
                                <acceleration>1500</acceleration>
                                <deceleration>1500</deceleration>
                                <jump-strength>650</jump-strength>
                                <gravity>1500</gravity>
                                <max-fall-speed>1000</max-fall-speed>
                                <double-jump>Disabled</double-jump>
                                <jump-sustain>0</jump-sustain>
                                <default-controls>No</default-controls>
                                <initial-state>Disabled</initial-state>
                            </properties>
                        </behavior-instance>
                    </behavior-instances>
                    <blend-mode>0</blend-mode>
                    <effect-fallback>0</effect-fallback>
                    <world>
                        <x>432</x>
                        <y>-91</y>
                        <z>0</z>
                        <width>39.611824036</width>
                        <height>43.212898254</height>
                        <depth>0</depth>
                        <hotspotX>0.5</hotspotX>
                        <hotspotY>0.5</hotspotY>
                        <angle>0</angle>
                        <opacity>1</opacity>
                    </world>
                </instance>
                <instance type="berrySmall" uid="98">
                    <properties>
                        <initial-visibility>Visible</initial-visibility>
                        <initial-animation>Default</initial-animation>
                        <initial-frame>0</initial-frame>
                        <collisions>Enabled</collisions>
                    </properties>
                    <behavior-instances>
                        <behavior-instance type="Bullet">
                            <properties>
                                <speed>0</speed>
                                <acceleration>0</acceleration>
                                <gravity>300</gravity>
                                <bounce-off-solids>No</bounce-off-solids>
                                <set-angle>No</set-angle>
                                <initial-state>Enabled</initial-state>
                            </properties>
                        </behavior-instance>
                        <behavior-instance type="Rotate">
                            <properties>
                                <speed>180</speed>
                                <acceleration>0</acceleration>
                            </properties>
                        </behavior-instance>
                        <behavior-instance type="Platform">
                            <properties>
                                <max-speed>330</max-speed>
                                <acceleration>1500</acceleration>
                                <deceleration>1500</deceleration>
                                <jump-strength>650</jump-strength>
                                <gravity>1500</gravity>
                                <max-fall-speed>1000</max-fall-speed>
                                <double-jump>Disabled</double-jump>
                                <jump-sustain>0</jump-sustain>
                                <default-controls>No</default-controls>
                                <initial-state>Disabled</initial-state>
                            </properties>
                        </behavior-instance>
                    </behavior-instances>
                    <blend-mode>0</blend-mode>
                    <effect-fallback>0</effect-fallback>
                    <world>
                        <x>580.727050781</x>
                        <y>-91.082305908</y>
                        <z>0</z>
                        <width>39.119758606</width>
                        <height>50.181209564</height>
                        <depth>0</depth>
                        <hotspotX>0.503448248</hotspotX>
                        <hotspotY>0.505376339</hotspotY>
                        <angle>0</angle>
                        <opacity>1</opacity>
                    </world>
                </instance>
                <instance type="plus1" uid="100">
                    <properties>
                        <character-width>16</character-width>
                        <character-height>16</character-height>
                        <character-set>ABCDEFGHIJKLMNOPQRSTUVWXYZabcdefghijklmnopqrstuvwxyz0123456789.,;:?!-_~#&quot;&apos;&amp;()[]|`\/@°+=*$£€&lt;&gt;</character-set>
                        <text>+1</text>
                        <scale>2</scale>
                        <initial-visibility>Visible</initial-visibility>
                        <horizontal-alignment>Center</horizontal-alignment>
                        <vertical-alignment>Center</vertical-alignment>
                        <hotspot>Center</hotspot>
                        <wrapping>Word</wrapping>
                        <character-spacing>0</character-spacing>
                        <line-height>0</line-height>
                    </properties>
                    <behavior-instances>
                        <behavior-instance type="Bullet">
                            <properties>
                                <speed>20</speed>
                                <acceleration>0</acceleration>
                                <gravity>0</gravity>
                                <bounce-off-solids>No</bounce-off-solids>
                                <set-angle>No</set-angle>
                                <initial-state>Enabled</initial-state>
                            </properties>
                        </behavior-instance>
                    </behavior-instances>
                    <blend-mode>0</blend-mode>
                    <effect-fallback>0</effect-fallback>
                    <world>
                        <x>-323</x>
                        <y>663</y>
                        <z>0</z>
                        <width>115</width>
                        <height>75</height>
                        <depth>0</depth>
                        <hotspotX>0.5</hotspotX>
                        <hotspotY>0.5</hotspotY>
                        <angle>0</angle>
                        <opacity>1</opacity>
                    </world>
                </instance>
                <instance type="plus2" uid="101">
                    <properties>
                        <character-width>16</character-width>
                        <character-height>16</character-height>
                        <character-set>ABCDEFGHIJKLMNOPQRSTUVWXYZabcdefghijklmnopqrstuvwxyz0123456789.,;:?!-_~#&quot;&apos;&amp;()[]|`\/@°+=*$£€&lt;&gt;</character-set>
                        <text>+2</text>
                        <scale>3</scale>
                        <initial-visibility>Visible</initial-visibility>
                        <horizontal-alignment>Center</horizontal-alignment>
                        <vertical-alignment>Center</vertical-alignment>
                        <hotspot>Center</hotspot>
                        <wrapping>Word</wrapping>
                        <character-spacing>0</character-spacing>
                        <line-height>0</line-height>
                    </properties>
                    <behavior-instances>
                        <behavior-instance type="Bullet">
                            <properties>
                                <speed>20</speed>
                                <acceleration>0</acceleration>
                                <gravity>0</gravity>
                                <bounce-off-solids>No</bounce-off-solids>
                                <set-angle>No</set-angle>
                                <initial-state>Enabled</initial-state>
                            </properties>
                        </behavior-instance>
                    </behavior-instances>
                    <blend-mode>0</blend-mode>
                    <effect-fallback>0</effect-fallback>
                    <world>
                        <x>-251</x>
                        <y>499</y>
                        <z>0</z>
                        <width>115</width>
                        <height>75</height>
                        <depth>0</depth>
                        <hotspotX>0.5</hotspotX>
                        <hotspotY>0.5</hotspotY>
                        <angle>0</angle>
                        <opacity>1</opacity>
                    </world>
                </instance>
            </instances>
            <effects />
        </layer>
        <layer name="Fade" sid="520791383037433">
            <initially-visible>1</initially-visible>
            <background-color>255,255,255</background-color>
            <transparent>1</transparent>
            <parallax>
                <x>1</x>
                <y>1</y>
            </parallax>
            <zoom-rate>1</zoom-rate>
            <opacity>1</opacity>
            <force-own-texture>0</force-own-texture>
            <global>0</global>
            <use-render-cells>0</use-render-cells>
            <blend-mode>0</blend-mode>
            <effect-fallback>0</effect-fallback>
            <instances>
                <instance type="FadeBlack" uid="37">
                    <properties>
                        <initial-visibility>Visible</initial-visibility>
                        <initial-animation>Default</initial-animation>
                        <initial-frame>0</initial-frame>
                        <collisions>Enabled</collisions>
                    </properties>
                    <behavior-instances>
                        <behavior-instance type="Fade">
                            <properties>
                                <active-at-start>No</active-at-start>
                                <fade-in-time>1.5</fade-in-time>
                                <wait-time>0</wait-time>
                                <fade-out-time>1</fade-out-time>
                                <destroy>No</destroy>
                            </properties>
                        </behavior-instance>
                    </behavior-instances>
                    <blend-mode>0</blend-mode>
                    <effect-fallback>0</effect-fallback>
                    <world>
                        <x>317</x>
                        <y>489</y>
                        <z>0</z>
                        <width>662</width>
                        <height>1019</height>
                        <depth>0</depth>
                        <hotspotX>0.5</hotspotX>
                        <hotspotY>0.5</hotspotY>
                        <angle>0</angle>
                        <opacity>0</opacity>
                    </world>
                </instance>
                <instance type="FadeStart" uid="95">
                    <properties>
                        <initial-visibility>Visible</initial-visibility>
                        <initial-animation>Default</initial-animation>
                        <initial-frame>0</initial-frame>
                        <collisions>Enabled</collisions>
                    </properties>
                    <behavior-instances>
                        <behavior-instance type="Fade">
                            <properties>
                                <active-at-start>Yes</active-at-start>
                                <fade-in-time>0</fade-in-time>
                                <wait-time>0</wait-time>
                                <fade-out-time>1</fade-out-time>
                                <destroy>No</destroy>
                            </properties>
                        </behavior-instance>
                    </behavior-instances>
                    <blend-mode>0</blend-mode>
                    <effect-fallback>0</effect-fallback>
                    <world>
                        <x>325.5</x>
                        <y>490</y>
                        <z>0</z>
                        <width>675</width>
                        <height>998</height>
                        <depth>0</depth>
                        <hotspotX>0.5</hotspotX>
                        <hotspotY>0.5</hotspotY>
                        <angle>0</angle>
                        <opacity>0</opacity>
                    </world>
                </instance>
            </instances>
            <effects />
        </layer>
        <layer name="End" sid="188646516156755">
            <initially-visible>1</initially-visible>
            <background-color>255,255,255</background-color>
            <transparent>1</transparent>
            <parallax>
                <x>1</x>
                <y>1</y>
            </parallax>
            <zoom-rate>1</zoom-rate>
            <opacity>1</opacity>
            <force-own-texture>0</force-own-texture>
            <global>0</global>
            <use-render-cells>0</use-render-cells>
            <blend-mode>0</blend-mode>
            <effect-fallback>0</effect-fallback>
            <instances>
                <instance type="muteButton" uid="32">
                    <properties>
                        <initial-visibility>Visible</initial-visibility>
                        <initial-animation>Default</initial-animation>
                        <initial-frame>0</initial-frame>
                        <collisions>Enabled</collisions>
                    </properties>
                    <blend-mode>0</blend-mode>
                    <effect-fallback>0</effect-fallback>
                    <world>
                        <x>208</x>
                        <y>-43</y>
                        <z>0</z>
                        <width>58.5</width>
                        <height>33.75</height>
                        <depth>0</depth>
                        <hotspotX>0.5</hotspotX>
                        <hotspotY>0.51111114</hotspotY>
                        <angle>0</angle>
                        <opacity>1</opacity>
                    </world>
                </instance>
                <instance type="homeButton" uid="82">
                    <properties>
                        <initial-visibility>Visible</initial-visibility>
                        <initial-animation>Default</initial-animation>
                        <initial-frame>0</initial-frame>
                        <collisions>Enabled</collisions>
                    </properties>
                    <blend-mode>0</blend-mode>
                    <effect-fallback>0</effect-fallback>
                    <world>
                        <x>335</x>
                        <y>-42</y>
                        <z>0</z>
                        <width>48</width>
                        <height>48</height>
                        <depth>0</depth>
                        <hotspotX>0.5</hotspotX>
                        <hotspotY>0.5</hotspotY>
                        <angle>0</angle>
                        <opacity>1</opacity>
                    </world>
                </instance>
                <instance type="endBG" uid="83">
                    <properties>
                        <initial-visibility>Visible</initial-visibility>
                        <hotspot>Top-left</hotspot>
                    </properties>
                    <blend-mode>0</blend-mode>
                    <effect-fallback>0</effect-fallback>
                    <world>
                        <x>720</x>
                        <y>720</y>
                        <z>0</z>
                        <width>640</width>
                        <height>960</height>
                        <depth>0</depth>
                        <hotspotX>0</hotspotX>
                        <hotspotY>0</hotspotY>
                        <angle>0</angle>
                        <opacity>1</opacity>
                    </world>
                </instance>
                <instance type="restartButton" uid="84">
                    <properties>
                        <initial-visibility>Visible</initial-visibility>
                        <initial-animation>Default</initial-animation>
                        <initial-frame>0</initial-frame>
                        <collisions>Enabled</collisions>
                    </properties>
                    <blend-mode>0</blend-mode>
                    <effect-fallback>0</effect-fallback>
                    <world>
                        <x>322</x>
                        <y>745</y>
                        <z>0</z>
                        <width>196</width>
                        <height>128</height>
                        <depth>0</depth>
                        <hotspotX>0.5</hotspotX>
                        <hotspotY>0.5</hotspotY>
                        <angle>0</angle>
                        <opacity>1</opacity>
                    </world>
                </instance>
                <instance type="titleButton" uid="85">
                    <properties>
                        <initial-visibility>Visible</initial-visibility>
                        <initial-animation>Default</initial-animation>
                        <initial-frame>0</initial-frame>
                        <collisions>Enabled</collisions>
                    </properties>
                    <blend-mode>0</blend-mode>
                    <effect-fallback>0</effect-fallback>
                    <world>
                        <x>322</x>
                        <y>533</y>
                        <z>0</z>
                        <width>196</width>
                        <height>128</height>
                        <depth>0</depth>
                        <hotspotX>0.5</hotspotX>
                        <hotspotY>0.5</hotspotY>
                        <angle>0</angle>
                        <opacity>1</opacity>
                    </world>
                </instance>
                <instance type="PandaFall" uid="87">
                    <properties>
                        <initial-visibility>Visible</initial-visibility>
                        <initial-animation>Default</initial-animation>
                        <initial-frame>0</initial-frame>
                        <collisions>Enabled</collisions>
                    </properties>
                    <behavior-instances>
                        <behavior-instance type="Sine">
                            <properties>
                                <active-on-start>Yes</active-on-start>
                                <movement>Vertical</movement>
                                <wave>Sine</wave>
                                <period>4</period>
                                <period-random>0</period-random>
                                <period-offset>0</period-offset>
                                <period-offset-random>0</period-offset-random>
                                <magnitude>50</magnitude>
                                <magnitude-random>0</magnitude-random>
                            </properties>
                        </behavior-instance>
                    </behavior-instances>
                    <blend-mode>0</blend-mode>
                    <effect-fallback>0</effect-fallback>
                    <world>
                        <x>320</x>
                        <y>-170</y>
                        <z>0</z>
                        <width>184</width>
                        <height>124</height>
                        <depth>0</depth>
                        <hotspotX>0.5</hotspotX>
                        <hotspotY>0.5</hotspotY>
                        <angle>0</angle>
                        <opacity>1</opacity>
                    </world>
                </instance>
                <instance type="Panda_Tear" uid="66">
                    <properties>
                        <initial-visibility>Visible</initial-visibility>
                        <initial-animation>Default</initial-animation>
                        <initial-frame>0</initial-frame>
                        <collisions>Enabled</collisions>
                    </properties>
                    <behavior-instances>
                        <behavior-instance type="Bullet">
                            <properties>
                                <speed>0</speed>
                                <acceleration>0</acceleration>
                                <gravity>-400</gravity>
                                <bounce-off-solids>No</bounce-off-solids>
                                <set-angle>Yes</set-angle>
                                <initial-state>Enabled</initial-state>
                            </properties>
                        </behavior-instance>
                    </behavior-instances>
                    <blend-mode>0</blend-mode>
                    <effect-fallback>0</effect-fallback>
                    <world>
                        <x>755</x>
                        <y>360</y>
                        <z>0</z>
                        <width>16</width>
                        <height>16</height>
                        <depth>0</depth>
                        <hotspotX>0.5</hotspotX>
                        <hotspotY>0.5</hotspotY>
                        <angle>-1.57079649</angle>
                        <opacity>1</opacity>
                    </world>
                </instance>
            </instances>
            <effects />
        </layer>
        <layer name="UI" sid="820483346861063">
            <initially-visible>1</initially-visible>
            <background-color>255,255,255</background-color>
            <transparent>1</transparent>
            <parallax>
                <x>1</x>
                <y>1</y>
            </parallax>
            <zoom-rate>1</zoom-rate>
            <opacity>1</opacity>
            <force-own-texture>0</force-own-texture>
            <global>0</global>
            <use-render-cells>0</use-render-cells>
            <blend-mode>0</blend-mode>
            <effect-fallback>0</effect-fallback>
            <instances>
                <instance type="tiledBG" uid="97">
                    <properties>
                        <initial-visibility>Visible</initial-visibility>
                        <hotspot>Center</hotspot>
                    </properties>
                    <blend-mode>0</blend-mode>
                    <effect-fallback>0</effect-fallback>
                    <world>
                        <x>324</x>
                        <y>1073</y>
                        <z>0</z>
                        <width>650</width>
                        <height>43.452747345</height>
                        <depth>0</depth>
                        <hotspotX>0.5</hotspotX>
                        <hotspotY>0.5</hotspotY>
                        <angle>0</angle>
                        <opacity>0.400000006</opacity>
                    </world>
                </instance>
                <instance type="Pause" uid="94">
                    <properties>
                        <initial-visibility>Visible</initial-visibility>
                        <initial-animation>Default</initial-animation>
                        <initial-frame>0</initial-frame>
                        <collisions>Enabled</collisions>
                    </properties>
                    <blend-mode>0</blend-mode>
                    <effect-fallback>0</effect-fallback>
                    <world>
                        <x>-64</x>
                        <y>-64</y>
                        <z>0</z>
                        <width>64</width>
                        <height>64</height>
                        <depth>0</depth>
                        <hotspotX>0.5</hotspotX>
                        <hotspotY>0.5</hotspotY>
                        <angle>0</angle>
                        <opacity>1</opacity>
                    </world>
                </instance>
                <instance type="scoreBG" uid="34">
                    <properties>
                        <initial-visibility>Visible</initial-visibility>
                        <initial-animation>Default</initial-animation>
                        <initial-frame>0</initial-frame>
                        <collisions>Enabled</collisions>
                    </properties>
                    <blend-mode>0</blend-mode>
                    <effect-fallback>0</effect-fallback>
                    <world>
                        <x>322</x>
                        <y>958</y>
                        <z>0</z>
                        <width>643.89440918</width>
                        <height>80.486801147</height>
                        <depth>0</depth>
                        <hotspotX>0.503125012</hotspotX>
                        <hotspotY>0.550000012</hotspotY>
                        <angle>0</angle>
                        <opacity>1</opacity>
                    </world>
                </instance>
                <instance type="Score" uid="33">
                    <properties>
                        <character-width>16</character-width>
                        <character-height>16</character-height>
                        <character-set>ABCDEFGHIJKLMNOPQRSTUVWXYZabcdefghijklmnopqrstuvwxyz0123456789.,;:?!-_~#&quot;&apos;&amp;()[]|`\/@°+=*$£€&lt;&gt;</character-set>
                        <text>Score</text>
                        <scale>2</scale>
                        <initial-visibility>Visible</initial-visibility>
                        <horizontal-alignment>Center</horizontal-alignment>
                        <vertical-alignment>Center</vertical-alignment>
                        <hotspot>Center</hotspot>
                        <wrapping>Word</wrapping>
                        <character-spacing>0</character-spacing>
                        <line-height>0</line-height>
                    </properties>
                    <blend-mode>0</blend-mode>
                    <effect-fallback>0</effect-fallback>
                    <world>
                        <x>320</x>
                        <y>937.771240234</y>
                        <z>0</z>
                        <width>403.234008789</width>
                        <height>44.457515717</height>
                        <depth>0</depth>
                        <hotspotX>0.5</hotspotX>
                        <hotspotY>0.5</hotspotY>
                        <angle>0</angle>
                        <opacity>1</opacity>
                    </world>
                </instance>
            </instances>
            <effects />
        </layer>
    </layers>
    <nonworld-instances />
    <effects />
</c2layout>
